bols/__init__.py
bols/regression.py
bols/tests.py
bols-0.0.1.dist-info/LICENSE.txt
bols-0.0.1.dist-info/METADATA
bols-0.0.1.dist-info/WHEEL
bols-0.0.1.dist-info/top_level.txt
bols-0.0.1.dist-info/RECORD
